cgrates/__init__.py
cgrates/models.py
cgrates/schema.py
cgrates/client/__init__.py
cgrates/client/apier_v1.py
cgrates/client/apier_v2.py
cgrates/client/base.py
cgrates/client/cdrs_v1.py
py_cgrates-0.0.5.dist-info/METADATA
py_cgrates-0.0.5.dist-info/WHEEL
py_cgrates-0.0.5.dist-info/top_level.txt
py_cgrates-0.0.5.dist-info/RECORD
