Metadata-Version: 2.1
Name: py-cgrates
Version: 0.0.5
Summary: Py CGRrateS
Home-page: https://github.com/hampsterx/py-cgrates
Author: Tim van der Hulst
Author-email: tim.vdh@gmail.com
License: GNU General Public License v3.0
Platform: UNKNOWN
Classifier: Development Status :: 4 - Beta
Classifier: Intended Audience :: System Administrators
Classifier: License :: OSI Approved :: GNU General Public License (GPL)
Classifier: Programming Language :: Python :: 3
Requires-Dist: schematics (==2.1.0)
Requires-Dist: rfc3339 (==6.0)
